{
	"response": [
		{
			"maintainer": "",
			"oem": "",
			"device": "",
			"filename": "crDroidAndroid-13.0-20230903-Spacewar-v9.8-microg.zip",
			"download": "https://sourceforge.net/projects/bernies-builds/files/Spacewar/microg/crDroidAndroid-13.0-20230903-Spacewar-v9.8-microg.zip/download",
			"timestamp": 1693741659,
			"md5": "a0e3b4ac2fc934a945828c0ff8d570bf",
			"sha256": "8aef9715c413a5928c3f5f41d4421891d4ad7d7873803ad41c44dada48317b27",
			"size": 2161578283,
			"version": "microg",
			"buildtype": "",
			"forum": "",
			"gapps": "",
			"firmware": "",
			"modem": "",
			"bootloader": "",
			"recovery": "",
			"paypal": "",
			"telegram": "",
			"dt": "",
			"common-dt": "",
			"kernel": ""
		}
	]
}
